caddy_cloudflare_cli-1.1.6.dist-info/METADATA
caddy_cloudflare_cli-1.1.6.dist-info/WHEEL
caddy_cloudflare_cli-1.1.6.dist-info/entry_points.txt
caddy_cloudflare_cli-1.1.6.dist-info/licenses/LICENSE.txt
caddy_cloudflare_cli/__init__.py
caddy_cloudflare_cli/cli.py
caddy_cloudflare_cli/lib/__init__.py
caddy_cloudflare_cli/lib/cloudflare_handler/__init__.py
caddy_cloudflare_cli/lib/cloudflare_handler/cloudflare_handler.py
caddy_cloudflare_cli/lib/cmd/__init__.py
caddy_cloudflare_cli/lib/cmd/debug.py
caddy_cloudflare_cli/lib/cmd/deploy.py
caddy_cloudflare_cli/lib/cmd/domain.py
caddy_cloudflare_cli/lib/cmd/init.py
caddy_cloudflare_cli/lib/cmd/install.py
caddy_cloudflare_cli/lib/cmd/manage.py
caddy_cloudflare_cli/lib/cmd/port.py
caddy_cloudflare_cli/lib/cmd/proxy.py
caddy_cloudflare_cli/lib/config.py
caddy_cloudflare_cli/lib/dns/base.py
caddy_cloudflare_cli/lib/dns/cloudflare_api_handler.py
caddy_cloudflare_cli/lib/factory.py
caddy_cloudflare_cli/lib/proxy/__init__.py
caddy_cloudflare_cli/lib/proxy/base.py
caddy_cloudflare_cli/lib/proxy/caddy/Caddyfile_templates/Caddyfile
caddy_cloudflare_cli/lib/proxy/caddy/Caddyfile_templates/Caddyfile_update
caddy_cloudflare_cli/lib/proxy/caddy/__init__.py
caddy_cloudflare_cli/lib/proxy/caddy/caddy.py
caddy_cloudflare_cli/lib/proxy/caddy/caddyfile.py
caddy_cloudflare_cli/lib/utils.py
caddy_cloudflare_cli-1.1.6.dist-info/RECORD
