Metadata-Version: 2.1
Name: caddy-cloudflare-cli
Version: 1.1.6
Summary: A powerful CLI tool for setting up and managing Cloudflare DNS records with Caddy reverse proxy. Easily deploy local services with public domains, automate DNS configuration, and manage SSL certificates using Cloudflare's API.
Author-Email: Tadeas Fort <business@tadeasfort.com>
License: GPL-3.0
Requires-Python: >=3.11
Requires-Dist: pyyaml>=6.0.1
Requires-Dist: python-dotenv>=1.0.0
Requires-Dist: requests>=2.31.0
Requires-Dist: typer>=0.15.2
Requires-Dist: cloudflare>=4.0.0
